[{"style":{"width":"10.214106334826702%","height":"63.64372377400252%","position":"absolute","left":"67.37918580612178%","top":"3.1455157940330025%","box-shadow":"none","bottom":"28.58586345057305%","right":"78.84196253106245%"},"contentStyle":{"overflow-y":"visible","padding":"0px 0px 0px 0px","background":"#77e3f9","border-top-left-radius":"63px 82px","border-bottom-left-radius":"40px 40px:::generated:::","border-bottom-right-radius":"40px 40px:::generated:::"},"showHeader":false,"autoZIndex":false,"type":"BACKGROUND"},{"style":{"width":"13.230760225642946%","height":"61.314876887227676%","position":"absolute","left":"60.3154047777768%","top":"8.690279813354302%","box-shadow":"none","bottom":"35.21315583959959%","right":"43.46366895021104%"},"contentStyle":{"overflow-y":"visible","padding":"0px 0px 0px 0px","background":"#84b850","border-top-left-radius":"3px 31px","border-bottom-left-radius":"40px 40px:::generated:::","border-bottom-right-radius":"40px 40px:::generated:::"},"showHeader":false,"autoZIndex":false,"type":"BACKGROUND"},{"style":{"width":"19.047011342106387%","height":"26.831431115146678%","position":"absolute","left":"32.31175608163822%","top":"43.51029595514376%","box-shadow":"none","bottom":"58.665303034304216%","right":"64.5846410320235%"},"contentStyle":{"overflow-y":"visible","padding":"0px 0px 0px 0px","background":"#e07773","border-top-left-radius":"27px 85px","border-bottom-left-radius":"40px 40px:::generated:::","border-bottom-right-radius":"40px 40px:::generated:::"},"showHeader":false,"autoZIndex":false,"type":"BACKGROUND"},{"style":{"width":"9.106328783972344%","height":"10.642632412810812%","position":"absolute","left":"16.596291489183933%","top":"42.16119117615721%","box-shadow":"none","bottom":"15.709579614148197%","right":"51.751730268473%"},"contentStyle":{"overflow-y":"visible","padding":"0px 0px 0px 0px","background":"#bb9ac8","border-top-left-radius":"49px 16px","border-bottom-left-radius":"40px 40px:::generated:::","border-bottom-right-radius":"40px 40px:::generated:::"},"showHeader":false,"autoZIndex":false,"type":"BACKGROUND"},{"style":{"width":"71.24427264590001%","height":"4.286978287028411%","position":"absolute","left":"4.724847524128663%","top":"82.94198316657571%","box-shadow":"none","bottom":"13.933187160289393%","right":"25.444150719348727%"},"contentStyle":{"overflow-y":"visible","padding":"0px 0px 0px 0px","background":"#88f8a3","border-top-left-radius":"74px 62px","border-bottom-left-radius":"40px 40px:::generated:::","border-bottom-right-radius":"40px 40px:::generated:::"},"showHeader":false,"autoZIndex":false,"type":"BACKGROUND"},{"style":{"width":"73.1179400644146%","height":"66.36893709618298%","position":"absolute","left":"8.308754983015191%","top":"23.26090449210325%","box-shadow":"none","bottom":"27.662492847928256%","right":"17.44662273900427%"},"contentStyle":{"overflow-y":"visible","padding":"0px 0px 0px 0px","background":"#9a7bc7","border-top-left-radius":"32px 83px","border-bottom-left-radius":"40px 40px:::generated:::","border-bottom-right-radius":"40px 40px:::generated:::"},"showHeader":false,"autoZIndex":false,"type":"BACKGROUND"},{"style":{"width":"25.4688006923762%","height":"30.112375291289432%","position":"absolute","left":"61.140474608897605%","top":"19.31700919470702%","box-shadow":"none","bottom":"22.204650695652056%","right":"15.691248514034704%"},"textStyle":{"text-align":"center","font-size":"2.6576773027863165rem","font-weight":"bold"},"contentStyle":{"overflow-y":"visible","padding":"0px 0px 0px 0px","background":"rgb(0 0 0 / 0%)","color":"#a26984"},"type":"TEXT","text":"uFg1","showHeader":false,"autoZIndex":false},{"style":{"width":"16.651313943105784%","height":"6.4184130978492675%","position":"absolute","left":"74.90570458865804%","top":"7.262372619799329%","box-shadow":"none","bottom":"5.092697769308707%","right":"15.873719502796902%"},"textStyle":{"text-align":"center","font-size":"1.9900830561344258rem","font-weight":"bold"},"contentStyle":{"overflow-y":"visible","padding":"0px 0px 0px 0px","background":"rgb(0 0 0 / 0%)","color":"#ff3d72"},"type":"TEXT","text":"s1","showHeader":false,"autoZIndex":false},{"style":{"width":"25.81163406585999%","height":"2.002515842026206%","position":"absolute","left":"44.19768752686733%","top":"35.96713330974656%","box-shadow":"none","bottom":"11.393519562381279%","right":"61.256934742246685%"},"textStyle":{"text-align":"center","font-size":"2.4489361277786377rem","font-weight":"bold"},"contentStyle":{"overflow-y":"visible","padding":"0px 0px 0px 0px","background":"rgb(0 0 0 / 0%)","color":"#e91042"},"type":"TEXT","text":"UdI4TZzM7","showHeader":false,"autoZIndex":false},{"style":{"width":"3.0620589683124066%","height":"19.066632874837964%","position":"absolute","left":"47.52821768399116%","top":"43.803771026975795%","box-shadow":"none","bottom":"30.31256908800448%","right":"84.06434525143736%"},"textStyle":{"text-align":"center","font-size":"2.8026572147439412rem","font-weight":"bold"},"contentStyle":{"overflow-y":"visible","padding":"0px 0px 0px 0px","background":"rgb(0 0 0 / 0%)","color":"#d8f86"},"type":"TEXT","text":"3j9nnFprP","showHeader":false,"autoZIndex":false},{"style":{"width":"44.8009877581169%","height":"16.278999649622847%","position":"absolute","left":"22.25155339754263%","top":"53.19785532557128%","box-shadow":"none","bottom":"2.9088173943247284%","right":"11.123827050316947%"},"textStyle":{"text-align":"center","font-size":"1.2034374603870606rem","font-weight":"bold"},"contentStyle":{"overflow-y":"visible","padding":"0px 0px 0px 0px","background":"rgb(0 0 0 / 0%)","color":"#531f5e"},"type":"TEXT","text":"ngwtWTHip","showHeader":false,"autoZIndex":false},{"style":{"width":"60.13643647182402%","height":"32.174827602725166%","position":"absolute","left":"30.63212101647163%","top":"60.17042519616798%","box-shadow":"none","bottom":"25.38871335445915%","right":"3.961305226838533%"},"textStyle":{"text-align":"center","font-size":"1.5466018876864898rem","font-weight":"bold"},"contentStyle":{"overflow-y":"visible","padding":"0px 0px 0px 0px","background":"rgb(0 0 0 / 0%)","color":"#60356b"},"type":"TEXT","text":"qY4pukkpH","showHeader":false,"autoZIndex":false},{"style":{"width":"62.535833662052994%","height":"2.062667886558444%","position":"absolute","left":"26.48353235133294%","top":"94.06829449988233%","box-shadow":"none","bottom":"4.74741686790523%","right":"27.509681796519722%"},"textStyle":{"text-align":"center","font-size":"0.42848127807781855rem","font-weight":"bold"},"contentStyle":{"overflow-y":"visible","padding":"0px 0px 0px 0px","background":"rgb(0 0 0 / 0%)","color":"#a1a35c"},"type":"TEXT","text":"gt","showHeader":false,"autoZIndex":false}]