[{"style":{"width":"19.65240610956554%","height":"32.23275693911063%","position":"absolute","left":"9.981990088798959%","top":"36.22909710384501%","box-shadow":"none","bottom":"62.67344662866743%","right":"52.51610026728758%"},"contentStyle":{"overflow-y":"visible","padding":"0px 0px 0px 0px","background":"#e31b04","border-top-left-radius":"15px 42px","border-bottom-left-radius":"40px 40px:::generated:::","border-bottom-right-radius":"40px 40px:::generated:::"},"showHeader":false,"autoZIndex":false,"type":"BACKGROUND"},{"style":{"width":"18.012229879197577%","height":"53.31507891504599%","position":"absolute","left":"14.882653537979692%","top":"31.098113297721206%","box-shadow":"none","bottom":"13.500738437075697%","right":"5.915884547026472%"},"contentStyle":{"overflow-y":"visible","padding":"0px 0px 0px 0px","background":"#a66156","border-top-left-radius":"73px 16px","border-bottom-left-radius":"40px 40px:::generated:::","border-bottom-right-radius":"40px 40px:::generated:::"},"showHeader":false,"autoZIndex":false,"type":"BACKGROUND"},{"style":{"width":"32.612484261375684%","height":"8.9628496876472%","position":"absolute","left":"56.47491161555212%","top":"38.04087986760935%","box-shadow":"none","bottom":"59.13783169523836%","right":"61.058409649251075%"},"contentStyle":{"overflow-y":"visible","padding":"0px 0px 0px 0px","background":"#55dab3","border-top-left-radius":"49px 64px","border-bottom-left-radius":"40px 40px:::generated:::","border-bottom-right-radius":"40px 40px:::generated:::"},"showHeader":false,"autoZIndex":false,"type":"BACKGROUND"},{"style":{"width":"72.7722975853849%","height":"7.610071730794012%","position":"absolute","left":"21.58519339723756%","top":"18.502295895111573%","box-shadow":"none","bottom":"29.074345593554995%","right":"22.323291282205155%"},"contentStyle":{"overflow-y":"visible","padding":"0px 0px 0px 0px","background":"#3e0921","border-top-left-radius":"49px 86px","border-bottom-left-radius":"40px 40px:::generated:::","border-bottom-right-radius":"40px 40px:::generated:::"},"showHeader":false,"autoZIndex":false,"type":"BACKGROUND"},{"style":{"width":"13.91393610906264%","height":"41.99490649267506%","position":"absolute","left":"61.28746402619457%","top":"17.272350692396905%","box-shadow":"none","bottom":"13.51369890576018%","right":"56.05105283374204%"},"contentStyle":{"overflow-y":"visible","padding":"0px 0px 0px 0px","background":"#34e2c8","border-top-left-radius":"43px 25px","border-bottom-left-radius":"40px 40px:::generated:::","border-bottom-right-radius":"40px 40px:::generated:::"},"showHeader":false,"autoZIndex":false,"type":"BACKGROUND"},{"style":{"width":"6.966610616013469%","height":"43.92397791474952%","position":"absolute","left":"9.744977222140456%","top":"12.927797310287808%","box-shadow":"none","bottom":"40.3243646407956%","right":"29.700804500084665%"},"contentStyle":{"overflow-y":"visible","padding":"0px 0px 0px 0px","background":"#744fc3","border-top-left-radius":"21px 49px","border-bottom-left-radius":"40px 40px:::generated:::","border-bottom-right-radius":"40px 40px:::generated:::"},"showHeader":false,"autoZIndex":false,"type":"BACKGROUND"},{"style":{"width":"23.581699262414602%","height":"11.306295297688628%","position":"absolute","left":"62.639816331264434%","top":"76.83743554954808%","box-shadow":"none","bottom":"40.68395676050055%","right":"28.941995677471184%"},"contentStyle":{"overflow-y":"visible","padding":"0px 0px 0px 0px","background":"#5c8f63","border-top-left-radius":"57px 40px","border-bottom-left-radius":"40px 40px:::generated:::","border-bottom-right-radius":"40px 40px:::generated:::"},"showHeader":false,"autoZIndex":false,"type":"BACKGROUND"},{"style":{"width":"17.007575126269018%","height":"12.697743691691201%","position":"absolute","left":"23.503177921998443%","top":"37.38934803886841%","box-shadow":"none","bottom":"24.729253691649802%","right":"11.975518673244501%"},"contentStyle":{"overflow-y":"visible","padding":"0px 0px 0px 0px","background":"#2f02c3","border-top-left-radius":"38px 35px","border-bottom-left-radius":"40px 40px:::generated:::","border-bottom-right-radius":"40px 40px:::generated:::"},"showHeader":false,"autoZIndex":false,"type":"BACKGROUND"},{"style":{"width":"12.682315379962944%","height":"12.141572099428117%","position":"absolute","left":"44.70637980362638%","top":"76.11636460547285%","box-shadow":"none","bottom":"84.8741761288621%","right":"40.33681251778613%"},"contentStyle":{"overflow-y":"visible","padding":"0px 0px 0px 0px","background":"#10e1e0","border-top-left-radius":"24px 46px","border-bottom-left-radius":"40px 40px:::generated:::","border-bottom-right-radius":"40px 40px:::generated:::"},"showHeader":false,"autoZIndex":false,"type":"BACKGROUND"},{"style":{"width":"3.3624913921155866%","height":"14.363134698835196%","position":"absolute","left":"34.95287706124625%","top":"26.48339137926743%","box-shadow":"none","bottom":"27.17496645198036%","right":"15.876615851566982%"},"textStyle":{"text-align":"center","font-size":"0.6590290132165804rem","font-weight":"bold"},"contentStyle":{"overflow-y":"visible","padding":"0px 0px 0px 0px","background":"rgb(0 0 0 / 0%)","color":"#12e176"},"type":"TEXT","text":"C0w69D8","showHeader":false,"autoZIndex":false},{"style":{"width":"27.20184575662943%","height":"22.70307895285523%","position":"absolute","left":"13.273781612939445%","top":"50.43703793746368%","box-shadow":"none","bottom":"55.47189202303023%","right":"30.8305152237915%"},"textStyle":{"text-align":"center","font-size":"2.433086670830512rem","font-weight":"bold"},"contentStyle":{"overflow-y":"visible","padding":"0px 0px 0px 0px","background":"rgb(0 0 0 / 0%)","color":"#d09d76"},"type":"TEXT","text":"rnTah","showHeader":false,"autoZIndex":false},{"style":{"width":"19.468228508069906%","height":"48.31856029076829%","position":"absolute","left":"11.513772028864985%","top":"11.048629396901418%","box-shadow":"none","bottom":"9.786084744338531%","right":"14.386411753407842%"},"textStyle":{"text-align":"center","font-size":"1.2943929644209078rem","font-weight":"bold"},"contentStyle":{"overflow-y":"visible","padding":"0px 0px 0px 0px","background":"rgb(0 0 0 / 0%)","color":"#db787b"},"type":"TEXT","text":"hDZWHlKd","showHeader":false,"autoZIndex":false},{"style":{"width":"43.042802983785705%","height":"12.510697232887246%","position":"absolute","left":"20.495521754666946%","top":"2.96305983779159%","box-shadow":"none","bottom":"41.65722808264005%","right":"33.61754283733762%"},"textStyle":{"text-align":"center","font-size":"0.7513563324832411rem","font-weight":"bold"},"contentStyle":{"overflow-y":"visible","padding":"0px 0px 0px 0px","background":"rgb(0 0 0 / 0%)","color":"#cc791a"},"type":"TEXT","text":"M2n2q","showHeader":false,"autoZIndex":false},{"style":{"width":"19.55236639229652%","height":"12.851261589148862%","position":"absolute","left":"56.94763377689818%","top":"81.06629042158502%","box-shadow":"none","bottom":"74.21305531237903%","right":"64.71353101006378%"},"textStyle":{"text-align":"center","font-size":"0.6958657468339651rem","font-weight":"bold"},"contentStyle":{"overflow-y":"visible","padding":"0px 0px 0px 0px","background":"rgb(0 0 0 / 0%)","color":"#869d0d"},"type":"TEXT","text":"gC","showHeader":false,"autoZIndex":false},{"style":{"width":"13.993629641163295%","height":"42.074534100484684%","position":"absolute","left":"49.37149566028115%","top":"30.114886278117538%","box-shadow":"none","bottom":"28.72155842466151%","right":"63.683272723709365%"},"textStyle":{"text-align":"center","font-size":"1.7966270358370735rem","font-weight":"bold"},"contentStyle":{"overflow-y":"visible","padding":"0px 0px 0px 0px","background":"rgb(0 0 0 / 0%)","color":"#4dd605"},"type":"TEXT","text":"HLUc","showHeader":false,"autoZIndex":false},{"style":{"width":"29.096428658907612%","height":"36.263197244676356%","position":"absolute","left":"41.390253613447285%","top":"59.86461871799092%","box-shadow":"none","bottom":"9.046789103171903%","right":"68.26952890152828%"},"textStyle":{"text-align":"center","font-size":"0.420478871283823rem","font-weight":"bold"},"contentStyle":{"overflow-y":"visible","padding":"0px 0px 0px 0px","background":"rgb(0 0 0 / 0%)","color":"#cf179f"},"type":"TEXT","text":"Y","showHeader":false,"autoZIndex":false},{"style":{"width":"44.71241302296339%","height":"56.23740922970951%","position":"absolute","left":"49.65330197507493%","top":"31.79221741309265%","box-shadow":"none","bottom":"14.032821645186978%","right":"6.276935535012107%"},"textStyle":{"text-align":"center","font-size":"1.2708706649392836rem","font-weight":"bold"},"contentStyle":{"overflow-y":"visible","padding":"0px 0px 0px 0px","background":"rgb(0 0 0 / 0%)","color":"#c3d5ce"},"type":"TEXT","text":"jKV1e","showHeader":false,"autoZIndex":false},{"style":{"width":"25.15999960096798%","height":"9.017181588084682%","position":"absolute","left":"28.805586068863782%","top":"71.16758258756079%","box-shadow":"none","bottom":"16.607313702300956%","right":"56.46448067020874%"},"textStyle":{"text-align":"center","font-size":"0.8364492787221351rem","font-weight":"bold"},"contentStyle":{"overflow-y":"visible","padding":"0px 0px 0px 0px","background":"rgb(0 0 0 / 0%)","color":"#818757"},"type":"TEXT","text":"hBjj","showHeader":false,"autoZIndex":false},{"style":{"width":"51.000667299019334%","height":"25.412775581468367%","position":"absolute","left":"14.21900120211766%","top":"22.050890404085173%","box-shadow":"none","bottom":"53.03999151503685%","right":"29.98795566747073%"},"textStyle":{"text-align":"center","font-size":"1.2200755529197802rem","font-weight":"bold"},"contentStyle":{"overflow-y":"visible","padding":"0px 0px 0px 0px","background":"rgb(0 0 0 / 0%)","color":"#30daf1"},"type":"TEXT","text":"14OSexTv","showHeader":false,"autoZIndex":false},{"style":{"width":"25.28713410399152%","height":"63.325686211642825%","position":"absolute","left":"52.395576615473765%","top":"16.72288966879131%","box-shadow":"none","bottom":"6.832491285880543%","right":"10.577845887874034%"},"textStyle":{"text-align":"center","font-size":"0.6283791678824829rem","font-weight":"bold"},"contentStyle":{"overflow-y":"visible","padding":"0px 0px 0px 0px","background":"rgb(0 0 0 / 0%)","color":"#a71fb9"},"type":"TEXT","text":"xDYQgdqPQ","showHeader":false,"autoZIndex":false},{"style":{"width":"20.9143952248957%","height":"55.19311900300645%","position":"absolute","left":"54.657991583491295%","top":"9.65248875715939%","box-shadow":"none","bottom":"12.462286100126114%","right":"62.81212092884666%"},"textStyle":{"text-align":"center","font-size":"1.7919523622142766rem","font-weight":"bold"},"contentStyle":{"overflow-y":"visible","padding":"0px 0px 0px 0px","background":"rgb(0 0 0 / 0%)","color":"#160bde"},"type":"TEXT","text":"MveUVCuA","showHeader":false,"autoZIndex":false}]