[{"style":{"width":"2.9278458362661723%","height":"35.202821894838344%","position":"absolute","left":"38.655458782851944%","top":"23.882916003270644%","box-shadow":"none","bottom":"52.672182825534385%","right":"39.9786092571795%"},"contentStyle":{"overflow-y":"visible","padding":"0px 0px 0px 0px","background":"#820f0d","border-top-left-radius":"67px 3px","border-bottom-left-radius":"40px 40px:::generated:::","border-bottom-right-radius":"40px 40px:::generated:::"},"showHeader":false,"autoZIndex":false,"type":"BACKGROUND"},{"style":{"width":"6.389152237222767%","height":"2.6081108866439067%","position":"absolute","left":"80.98284701547185%","top":"68.96094575817494%","box-shadow":"none","bottom":"12.356727506259581%","right":"21.941112347442576%"},"contentStyle":{"overflow-y":"visible","padding":"0px 0px 0px 0px","background":"#806878","border-top-left-radius":"70px 97px","border-bottom-left-radius":"40px 40px:::generated:::","border-bottom-right-radius":"40px 40px:::generated:::"},"showHeader":false,"autoZIndex":false,"type":"BACKGROUND"},{"style":{"width":"16.4627595680141%","height":"10.089970331100211%","position":"absolute","left":"40.272907831086385%","top":"35.03455449997769%","box-shadow":"none","bottom":"53.59997672347157%","right":"24.16980167632523%"},"contentStyle":{"overflow-y":"visible","padding":"0px 0px 0px 0px","background":"#57e452","border-top-left-radius":"5px 97px","border-bottom-left-radius":"40px 40px:::generated:::","border-bottom-right-radius":"40px 40px:::generated:::"},"showHeader":false,"autoZIndex":false,"type":"BACKGROUND"},{"style":{"width":"9.427940993527308%","height":"43.16192570768415%","position":"absolute","left":"70.51127904877481%","top":"30.584734300086673%","box-shadow":"none","bottom":"9.46705469831047%","right":"65.5444989870706%"},"contentStyle":{"overflow-y":"visible","padding":"0px 0px 0px 0px","background":"#8d63dc","border-top-left-radius":"92px 26px","border-bottom-left-radius":"40px 40px:::generated:::","border-bottom-right-radius":"40px 40px:::generated:::"},"showHeader":false,"autoZIndex":false,"type":"BACKGROUND"},{"style":{"width":"36.73346735942448%","height":"2.478824904238003%","position":"absolute","left":"39.86493565156719%","top":"42.71900778848977%","box-shadow":"none","bottom":"59.0863566657625%","right":"31.996208574408556%"},"contentStyle":{"overflow-y":"visible","padding":"0px 0px 0px 0px","background":"#6135f","border-top-left-radius":"20px 13px","border-bottom-left-radius":"40px 40px:::generated:::","border-bottom-right-radius":"40px 40px:::generated:::"},"showHeader":false,"autoZIndex":false,"type":"BACKGROUND"},{"style":{"width":"33.97074534416723%","height":"9.646743243499436%","position":"absolute","left":"6.131236680727248%","top":"38.24525982925798%","box-shadow":"none","bottom":"57.33151897686374%","right":"22.384121127101793%"},"contentStyle":{"overflow-y":"visible","padding":"0px 0px 0px 0px","background":"#dfef64","border-top-left-radius":"30px 14px","border-bottom-left-radius":"40px 40px:::generated:::","border-bottom-right-radius":"40px 40px:::generated:::"},"showHeader":false,"autoZIndex":false,"type":"BACKGROUND"},{"style":{"width":"19.41877714249337%","height":"31.902275882622718%","position":"absolute","left":"68.16881851251733%","top":"10.591783128057997%","box-shadow":"none","bottom":"20.24687668624386%","right":"53.62506527196205%"},"contentStyle":{"overflow-y":"visible","padding":"0px 0px 0px 0px","background":"#ddb1bf","border-top-left-radius":"42px 81px","border-bottom-left-radius":"40px 40px:::generated:::","border-bottom-right-radius":"40px 40px:::generated:::"},"showHeader":false,"autoZIndex":false,"type":"BACKGROUND"},{"style":{"width":"27.485845089490986%","height":"20.307894780260703%","position":"absolute","left":"27.846457169024106%","top":"19.37355459202618%","box-shadow":"none","bottom":"53.406386475609686%","right":"51.573920687892425%"},"contentStyle":{"overflow-y":"visible","padding":"0px 0px 0px 0px","background":"#328144","border-top-left-radius":"82px 90px","border-bottom-left-radius":"40px 40px:::generated:::","border-bottom-right-radius":"40px 40px:::generated:::"},"showHeader":false,"autoZIndex":false,"type":"BACKGROUND"},{"style":{"width":"22.668727001148284%","height":"10.78991031583032%","position":"absolute","left":"40.04127991489914%","top":"51.49485747070173%","box-shadow":"none","bottom":"15.580391201119532%","right":"60.14465926392534%"},"contentStyle":{"overflow-y":"visible","padding":"0px 0px 0px 0px","background":"#353ce3","border-top-left-radius":"19px 21px","border-bottom-left-radius":"40px 40px:::generated:::","border-bottom-right-radius":"40px 40px:::generated:::"},"showHeader":false,"autoZIndex":false,"type":"BACKGROUND"},{"style":{"width":"76.97177344898529%","height":"11.711647101169326%","position":"absolute","left":"5.013123665605612%","top":"50.74483156020727%","box-shadow":"none","bottom":"29.97698008322987%","right":"13.257957782937737%"},"contentStyle":{"overflow-y":"visible","padding":"0px 0px 0px 0px","background":"#722426","border-top-left-radius":"27px 32px","border-bottom-left-radius":"40px 40px:::generated:::","border-bottom-right-radius":"40px 40px:::generated:::"},"showHeader":false,"autoZIndex":false,"type":"BACKGROUND"},{"style":{"width":"20.585704528093615%","height":"29.514382789152876%","position":"absolute","left":"3.7629688207240193%","top":"60.48662056693508%","box-shadow":"none","bottom":"7.88900219422149%","right":"72.54732950729597%"},"contentStyle":{"overflow-y":"visible","padding":"0px 0px 0px 0px","background":"#ce658","border-top-left-radius":"93px 7px","border-bottom-left-radius":"40px 40px:::generated:::","border-bottom-right-radius":"40px 40px:::generated:::"},"showHeader":false,"autoZIndex":false,"type":"BACKGROUND"},{"style":{"width":"32.206315703111244%","height":"14.47904321902164%","position":"absolute","left":"62.854886457575375%","top":"5.952417161627089%","box-shadow":"none","bottom":"70.47732102883874%","right":"61.685854492686516%"},"textStyle":{"text-align":"center","font-size":"2.681343546773242rem","font-weight":"bold"},"contentStyle":{"overflow-y":"visible","padding":"0px 0px 0px 0px","background":"rgb(0 0 0 / 0%)","color":"#1ea295"},"type":"TEXT","text":"rWd7","showHeader":false,"autoZIndex":false},{"style":{"width":"16.562159924815766%","height":"46.496917434941246%","position":"absolute","left":"16.87417549008535%","top":"49.95208571716585%","box-shadow":"none","bottom":"8.443390981080405%","right":"2.3990694097370806%"},"textStyle":{"text-align":"center","font-size":"0.45551656747672403rem","font-weight":"bold"},"contentStyle":{"overflow-y":"visible","padding":"0px 0px 0px 0px","background":"rgb(0 0 0 / 0%)","color":"#a9f8fe"},"type":"TEXT","text":"2T","showHeader":false,"autoZIndex":false},{"style":{"width":"18.29058808430503%","height":"33.89368295194547%","position":"absolute","left":"76.85756535983543%","top":"53.04862551520997%","box-shadow":"none","bottom":"56.268207204503696%","right":"9.419299343791884%"},"textStyle":{"text-align":"center","font-size":"1.7270475240225514rem","font-weight":"bold"},"contentStyle":{"overflow-y":"visible","padding":"0px 0px 0px 0px","background":"rgb(0 0 0 / 0%)","color":"#f4f2d1"},"type":"TEXT","text":"eLRTC0","showHeader":false,"autoZIndex":false},{"style":{"width":"36.09250275073258%","height":"5.499808111184436%","position":"absolute","left":"31.649857715762998%","top":"15.881127896408735%","box-shadow":"none","bottom":"45.36621141252662%","right":"23.424919378189394%"},"textStyle":{"text-align":"center","font-size":"2.296936195509026rem","font-weight":"bold"},"contentStyle":{"overflow-y":"visible","padding":"0px 0px 0px 0px","background":"rgb(0 0 0 / 0%)","color":"#b59354"},"type":"TEXT","text":"AZa3H","showHeader":false,"autoZIndex":false},{"style":{"width":"15.640170708405236%","height":"7.988434937849966%","position":"absolute","left":"43.67724912663595%","top":"29.242046967587598%","box-shadow":"none","bottom":"73.50110599231515%","right":"10.262013770746009%"},"textStyle":{"text-align":"center","font-size":"2.0827909940725657rem","font-weight":"bold"},"contentStyle":{"overflow-y":"visible","padding":"0px 0px 0px 0px","background":"rgb(0 0 0 / 0%)","color":"#4657f9"},"type":"TEXT","text":"xOAd7","showHeader":false,"autoZIndex":false},{"style":{"width":"21.64708248182329%","height":"15.613280550951515%","position":"absolute","left":"10.720700432663548%","top":"47.92422749379481%","box-shadow":"none","bottom":"3.229298676909252%","right":"34.951377086918804%"},"textStyle":{"text-align":"center","font-size":"2.1641054192319436rem","font-weight":"bold"},"contentStyle":{"overflow-y":"visible","padding":"0px 0px 0px 0px","background":"rgb(0 0 0 / 0%)","color":"#8b2e18"},"type":"TEXT","text":"AOm","showHeader":false,"autoZIndex":false},{"style":{"width":"32.88013509699476%","height":"72.08287958511315%","position":"absolute","left":"43.47759436683593%","top":"16.374005985312408%","box-shadow":"none","bottom":"22.628212021762764%","right":"51.708475459670865%"},"textStyle":{"text-align":"center","font-size":"0.7323693341978764rem","font-weight":"bold"},"contentStyle":{"overflow-y":"visible","padding":"0px 0px 0px 0px","background":"rgb(0 0 0 / 0%)","color":"#9eff4f"},"type":"TEXT","text":"T","showHeader":false,"autoZIndex":false},{"style":{"width":"21.303910631280743%","height":"44.82639602277622%","position":"absolute","left":"28.71609735978101%","top":"48.164438947939516%","box-shadow":"none","bottom":"5.500587484936531%","right":"36.22692202839201%"},"textStyle":{"text-align":"center","font-size":"0.846774804924916rem","font-weight":"bold"},"contentStyle":{"overflow-y":"visible","padding":"0px 0px 0px 0px","background":"rgb(0 0 0 / 0%)","color":"#d757a3"},"type":"TEXT","text":"Rv7wa","showHeader":false,"autoZIndex":false},{"style":{"width":"46.53338648548246%","height":"33.225084960831644%","position":"absolute","left":"30.819085151125826%","top":"18.986820613741692%","box-shadow":"none","bottom":"46.84376568860311%","right":"33.377484241640566%"},"textStyle":{"text-align":"center","font-size":"0.34911439346041184rem","font-weight":"bold"},"contentStyle":{"overflow-y":"visible","padding":"0px 0px 0px 0px","background":"rgb(0 0 0 / 0%)","color":"#ab2981"},"type":"TEXT","text":"CoEsX","showHeader":false,"autoZIndex":false},{"style":{"width":"26.827170442271303%","height":"14.583688552923924%","position":"absolute","left":"39.13804540744619%","top":"74.65458640529656%","box-shadow":"none","bottom":"31.39848344031367%","right":"35.89042433487026%"},"textStyle":{"text-align":"center","font-size":"0.5426370845688844rem","font-weight":"bold"},"contentStyle":{"overflow-y":"visible","padding":"0px 0px 0px 0px","background":"rgb(0 0 0 / 0%)","color":"#185d3a"},"type":"TEXT","text":"Ch","showHeader":false,"autoZIndex":false},{"style":{"width":"3.37875675158854%","height":"33.21596067782248%","position":"absolute","left":"57.656407277153484%","top":"26.111168660852705%","box-shadow":"none","bottom":"28.104792595312915%","right":"21.25532400675415%"},"textStyle":{"text-align":"center","font-size":"1.0215303895344245rem","font-weight":"bold"},"contentStyle":{"overflow-y":"visible","padding":"0px 0px 0px 0px","background":"rgb(0 0 0 / 0%)","color":"#137861"},"type":"TEXT","text":"Zdp7a04","showHeader":false,"autoZIndex":false},{"style":{"width":"56.74626919712624%","height":"22.847279645464177%","position":"absolute","left":"22.717447564977448%","top":"11.381852124503595%","box-shadow":"none","bottom":"13.716017082767259%","right":"40.084453235352086%"},"textStyle":{"text-align":"center","font-size":"0.7665548604422524rem","font-weight":"bold"},"contentStyle":{"overflow-y":"visible","padding":"0px 0px 0px 0px","background":"rgb(0 0 0 / 0%)","color":"#b11519"},"type":"TEXT","text":"jh8h19","showHeader":false,"autoZIndex":false},{"style":{"width":"18.1562719484684%","height":"27.81690779927162%","position":"absolute","left":"47.54664151955712%","top":"20.644947459940624%","box-shadow":"none","bottom":"6.1269511452601435%","right":"56.30532705670607%"},"textStyle":{"text-align":"center","font-size":"2.345818927965326rem","font-weight":"bold"},"contentStyle":{"overflow-y":"visible","padding":"0px 0px 0px 0px","background":"rgb(0 0 0 / 0%)","color":"#bcbae4"},"type":"TEXT","text":"x","showHeader":false,"autoZIndex":false},{"style":{"width":"2.1307540081963054%","height":"22.192052663917273%","position":"absolute","left":"75.23013963997687%","top":"70.15658761207203%","box-shadow":"none","bottom":"30.2794585575136%","right":"65.85098420444652%"},"textStyle":{"text-align":"center","font-size":"2.226742596511972rem","font-weight":"bold"},"contentStyle":{"overflow-y":"visible","padding":"0px 0px 0px 0px","background":"rgb(0 0 0 / 0%)","color":"#4989ce"},"type":"TEXT","text":"UNbiy","showHeader":false,"autoZIndex":false},{"style":{"width":"41.77047914107592%","height":"14.56988781344802%","position":"absolute","left":"10.48069450991727%","top":"16.764050580716415%","box-shadow":"none","bottom":"33.908992698790826%","right":"30.747742375933072%"},"textStyle":{"text-align":"center","font-size":"1.485594910001927rem","font-weight":"bold"},"contentStyle":{"overflow-y":"visible","padding":"0px 0px 0px 0px","background":"rgb(0 0 0 / 0%)","color":"#c51e7a"},"type":"TEXT","text":"Wmyru","showHeader":false,"autoZIndex":false},{"style":{"width":"2.9778567079821983%","height":"4.4912507193819025%","position":"absolute","left":"36.735426820584486%","top":"21.163825971318843%","box-shadow":"none","bottom":"52.78677020092398%","right":"92.69588277123357%"},"textStyle":{"text-align":"center","font-size":"0.9732270296880496rem","font-weight":"bold"},"contentStyle":{"overflow-y":"visible","padding":"0px 0px 0px 0px","background":"rgb(0 0 0 / 0%)","color":"#cb0274"},"type":"TEXT","text":"ey","showHeader":false,"autoZIndex":false},{"style":{"width":"85.8284767582891%","height":"3.8005764018471737%","position":"absolute","left":"3.169844576520582%","top":"5.192109991662839%","box-shadow":"none","bottom":"61.882670337676124%","right":"2.270007433149253%"},"textStyle":{"text-align":"center","font-size":"0.44166281889770986rem","font-weight":"bold"},"contentStyle":{"overflow-y":"visible","padding":"0px 0px 0px 0px","background":"rgb(0 0 0 / 0%)","color":"#1f0d3b"},"type":"TEXT","text":"p2pQ","showHeader":false,"autoZIndex":false},{"style":{"width":"49.06432279493332%","height":"41.97570597646477%","position":"absolute","left":"24.334180814355562%","top":"32.231425621814246%","box-shadow":"none","bottom":"9.699815924212011%","right":"6.4787957503940845%"},"textStyle":{"text-align":"center","font-size":"2.354016764189892rem","font-weight":"bold"},"contentStyle":{"overflow-y":"visible","padding":"0px 0px 0px 0px","background":"rgb(0 0 0 / 0%)","color":"#6a22c6"},"type":"TEXT","text":"9c","showHeader":false,"autoZIndex":false},{"style":{"width":"12.611195216499603%","height":"44.27649379059804%","position":"absolute","left":"82.45065549364188%","top":"37.06623298492698%","box-shadow":"none","bottom":"2.145181776479923%","right":"20.865103452429878%"},"textStyle":{"text-align":"center","font-size":"1.7881803532416756rem","font-weight":"bold"},"contentStyle":{"overflow-y":"visible","padding":"0px 0px 0px 0px","background":"rgb(0 0 0 / 0%)","color":"#992ae"},"type":"TEXT","text":"zj8pv","showHeader":false,"autoZIndex":false}]