[{"style":{"width":"42.34964620830704%","height":"18.410997235515005%","position":"absolute","left":"28.031820550325776%","top":"15.061924571877967%","box-shadow":"none","bottom":"34.97102780569276%","right":"15.878573038611563%"},"contentStyle":{"overflow-y":"visible","padding":"0px 0px 0px 0px","background":"#91867b","border-top-left-radius":"55px 95px","border-bottom-left-radius":"40px 40px:::generated:::","border-bottom-right-radius":"40px 40px:::generated:::"},"showHeader":false,"autoZIndex":false,"type":"BACKGROUND"},{"style":{"width":"19.713923451916855%","height":"33.840320443438685%","position":"absolute","left":"6.0720008863613515%","top":"33.04580872270157%","box-shadow":"none","bottom":"52.238012485399686%","right":"23.451706443465525%"},"contentStyle":{"overflow-y":"visible","padding":"0px 0px 0px 0px","background":"#dca73c","border-top-left-radius":"22px 57px","border-bottom-left-radius":"40px 40px:::generated:::","border-bottom-right-radius":"40px 40px:::generated:::"},"showHeader":false,"autoZIndex":false,"type":"BACKGROUND"},{"style":{"width":"22.127513392877553%","height":"44.61432411492368%","position":"absolute","left":"69.49063469672284%","top":"44.54288721790324%","box-shadow":"none","bottom":"40.71478354594061%","right":"68.96283034990915%"},"contentStyle":{"overflow-y":"visible","padding":"0px 0px 0px 0px","background":"#31dca4","border-top-left-radius":"17px 74px","border-bottom-left-radius":"40px 40px:::generated:::","border-bottom-right-radius":"40px 40px:::generated:::"},"showHeader":false,"autoZIndex":false,"type":"BACKGROUND"},{"style":{"width":"60.85567152164899%","height":"26.326418516010683%","position":"absolute","left":"19.765253085656752%","top":"5.88928418386088%","box-shadow":"none","bottom":"64.03066181781215%","right":"28.330781519868864%"},"contentStyle":{"overflow-y":"visible","padding":"0px 0px 0px 0px","background":"#3eb523","border-top-left-radius":"75px 96px","border-bottom-left-radius":"40px 40px:::generated:::","border-bottom-right-radius":"40px 40px:::generated:::"},"showHeader":false,"autoZIndex":false,"type":"BACKGROUND"},{"style":{"width":"28.407887732952332%","height":"18.937704827566755%","position":"absolute","left":"28.550206213858687%","top":"26.221353583186605%","box-shadow":"none","bottom":"42.887508424016396%","right":"38.32541610759587%"},"contentStyle":{"overflow-y":"visible","padding":"0px 0px 0px 0px","background":"#507e93","border-top-left-radius":"18px 20px","border-bottom-left-radius":"40px 40px:::generated:::","border-bottom-right-radius":"40px 40px:::generated:::"},"showHeader":false,"autoZIndex":false,"type":"BACKGROUND"},{"style":{"width":"39.48579959997138%","height":"43.508447148750705%","position":"absolute","left":"56.61026574449941%","top":"5.050445797679046%","box-shadow":"none","bottom":"30.545709604822584%","right":"33.08979293754289%"},"contentStyle":{"overflow-y":"visible","padding":"0px 0px 0px 0px","background":"#799c06","border-top-left-radius":"85px 17px","border-bottom-left-radius":"40px 40px:::generated:::","border-bottom-right-radius":"40px 40px:::generated:::"},"showHeader":false,"autoZIndex":false,"type":"BACKGROUND"},{"style":{"width":"29.378014829996808%","height":"19.994849421394953%","position":"absolute","left":"19.38234223253297%","top":"44.60772809583867%","box-shadow":"none","bottom":"38.89720803617817%","right":"55.02008539572914%"},"contentStyle":{"overflow-y":"visible","padding":"0px 0px 0px 0px","background":"#897fd2","border-top-left-radius":"81px 45px","border-bottom-left-radius":"40px 40px:::generated:::","border-bottom-right-radius":"40px 40px:::generated:::"},"showHeader":false,"autoZIndex":false,"type":"BACKGROUND"},{"style":{"width":"19.37517918126329%","height":"29.547276004711264%","position":"absolute","left":"75.85172387978186%","top":"37.52169675827887%","box-shadow":"none","bottom":"50.10569296116074%","right":"2.701136830508837%"},"contentStyle":{"overflow-y":"visible","padding":"0px 0px 0px 0px","background":"#d3ddee","border-top-left-radius":"28px 63px","border-bottom-left-radius":"40px 40px:::generated:::","border-bottom-right-radius":"40px 40px:::generated:::"},"showHeader":false,"autoZIndex":false,"type":"BACKGROUND"},{"style":{"width":"10.442031780959454%","height":"14.986860640492111%","position":"absolute","left":"75.42083532139816%","top":"16.08315737580071%","box-shadow":"none","bottom":"59.88230074022081%","right":"56.33894867256458%"},"textStyle":{"text-align":"center","font-size":"1.5051115098668106rem","font-weight":"bold"},"contentStyle":{"overflow-y":"visible","padding":"0px 0px 0px 0px","background":"rgb(0 0 0 / 0%)","color":"#6f487"},"type":"TEXT","text":"dXLRk","showHeader":false,"autoZIndex":false},{"style":{"width":"15.825147820994168%","height":"10.65359907180811%","position":"absolute","left":"77.8250547971239%","top":"80.0665003606793%","box-shadow":"none","bottom":"47.55389110452172%","right":"6.981358439058553%"},"textStyle":{"text-align":"center","font-size":"0.826052093617059rem","font-weight":"bold"},"contentStyle":{"overflow-y":"visible","padding":"0px 0px 0px 0px","background":"rgb(0 0 0 / 0%)","color":"#35a65e"},"type":"TEXT","text":"BYv5i","showHeader":false,"autoZIndex":false},{"style":{"width":"24.39815755976055%","height":"18.916991323719643%","position":"absolute","left":"64.72792697514964%","top":"14.04984145696519%","box-shadow":"none","bottom":"38.776200496466544%","right":"55.40472748474917%"},"textStyle":{"text-align":"center","font-size":"1.5540939820038728rem","font-weight":"bold"},"contentStyle":{"overflow-y":"visible","padding":"0px 0px 0px 0px","background":"rgb(0 0 0 / 0%)","color":"#54a42c"},"type":"TEXT","text":"oGvVRrv","showHeader":false,"autoZIndex":false},{"style":{"width":"31.098192376571085%","height":"18.362844722910545%","position":"absolute","left":"3.433544575510119%","top":"59.45117183200947%","box-shadow":"none","bottom":"57.383958390190415%","right":"61.064045573207615%"},"textStyle":{"text-align":"center","font-size":"1.250557633870905rem","font-weight":"bold"},"contentStyle":{"overflow-y":"visible","padding":"0px 0px 0px 0px","background":"rgb(0 0 0 / 0%)","color":"#565931"},"type":"TEXT","text":"TppEbl79","showHeader":false,"autoZIndex":false},{"style":{"width":"49.75421962327649%","height":"39.669658772078%","position":"absolute","left":"45.16165887647023%","top":"37.81412813072558%","box-shadow":"none","bottom":"38.64361975814141%","right":"33.75085762233714%"},"textStyle":{"text-align":"center","font-size":"2.137319356259912rem","font-weight":"bold"},"contentStyle":{"overflow-y":"visible","padding":"0px 0px 0px 0px","background":"rgb(0 0 0 / 0%)","color":"#19576a"},"type":"TEXT","text":"EHBk","showHeader":false,"autoZIndex":false},{"style":{"width":"28.009521555894274%","height":"3.801588929549048%","position":"absolute","left":"59.53988343996823%","top":"4.021968108997072%","box-shadow":"none","bottom":"14.013230873401682%","right":"8.314742998050136%"},"textStyle":{"text-align":"center","font-size":"1.2123751346571623rem","font-weight":"bold"},"contentStyle":{"overflow-y":"visible","padding":"0px 0px 0px 0px","background":"rgb(0 0 0 / 0%)","color":"#7fb0d5"},"type":"TEXT","text":"14r","showHeader":false,"autoZIndex":false},{"style":{"width":"7.440990996206182%","height":"17.588971395271948%","position":"absolute","left":"61.64889000192939%","top":"23.45672360755195%","box-shadow":"none","bottom":"18.658869599744428%","right":"29.785213175069885%"},"textStyle":{"text-align":"center","font-size":"0.5054016700934831rem","font-weight":"bold"},"contentStyle":{"overflow-y":"visible","padding":"0px 0px 0px 0px","background":"rgb(0 0 0 / 0%)","color":"#3c06c7"},"type":"TEXT","text":"Dz","showHeader":false,"autoZIndex":false},{"style":{"width":"18.103047559953218%","height":"18.639706482494766%","position":"absolute","left":"67.55608748292755%","top":"21.361872184076503%","box-shadow":"none","bottom":"77.15194140072524%","right":"31.013269480044613%"},"textStyle":{"text-align":"center","font-size":"1.0532147096521058rem","font-weight":"bold"},"contentStyle":{"overflow-y":"visible","padding":"0px 0px 0px 0px","background":"rgb(0 0 0 / 0%)","color":"#bbb26b"},"type":"TEXT","text":"2","showHeader":false,"autoZIndex":false},{"style":{"width":"59.25133008389076%","height":"6.9121053608633645%","position":"absolute","left":"29.772406895421213%","top":"55.12024796391141%","box-shadow":"none","bottom":"22.408886499131427%","right":"35.821790500893854%"},"textStyle":{"text-align":"center","font-size":"2.7943265987052577rem","font-weight":"bold"},"contentStyle":{"overflow-y":"visible","padding":"0px 0px 0px 0px","background":"rgb(0 0 0 / 0%)","color":"#c56dd0"},"type":"TEXT","text":"82gW8CUVg","showHeader":false,"autoZIndex":false},{"style":{"width":"6.043855900826912%","height":"32.801224714254616%","position":"absolute","left":"58.21860981974632%","top":"58.00623859625433%","box-shadow":"none","bottom":"9.966699463359099%","right":"54.54193172387102%"},"textStyle":{"text-align":"center","font-size":"2.354030896665458rem","font-weight":"bold"},"contentStyle":{"overflow-y":"visible","padding":"0px 0px 0px 0px","background":"rgb(0 0 0 / 0%)","color":"#4d9fb5"},"type":"TEXT","text":"hf","showHeader":false,"autoZIndex":false},{"style":{"width":"36.56491629831762%","height":"32.79956103153394%","position":"absolute","left":"23.018889875362945%","top":"17.55111489265488%","box-shadow":"none","bottom":"55.31947661029658%","right":"30.35079182951098%"},"textStyle":{"text-align":"center","font-size":"2.5843121056019625rem","font-weight":"bold"},"contentStyle":{"overflow-y":"visible","padding":"0px 0px 0px 0px","background":"rgb(0 0 0 / 0%)","color":"#bb8fd5"},"type":"TEXT","text":"dkAO","showHeader":false,"autoZIndex":false},{"style":{"width":"51.980072110351344%","height":"68.16033459452456%","position":"absolute","left":"8.124503988935494%","top":"29.46386891996263%","box-shadow":"none","bottom":"5.934855841957273%","right":"40.88042629590699%"},"textStyle":{"text-align":"center","font-size":"0.7665818533890956rem","font-weight":"bold"},"contentStyle":{"overflow-y":"visible","padding":"0px 0px 0px 0px","background":"rgb(0 0 0 / 0%)","color":"#75003e"},"type":"TEXT","text":"JpS62UhbI","showHeader":false,"autoZIndex":false}]