[{"style":{"width":"11.863550663995873%","height":"18.46434827564333%","position":"absolute","left":"53.32165072819327%","top":"51.50801898619967%","box-shadow":"none","bottom":"29.05172621117351%","right":"13.298727461015432%"},"contentStyle":{"overflow-y":"visible","padding":"0px 0px 0px 0px","background":"#85c77d","border-top-left-radius":"13px 22px","border-bottom-left-radius":"40px 40px:::generated:::","border-bottom-right-radius":"40px 40px:::generated:::"},"showHeader":false,"autoZIndex":false,"type":"BACKGROUND"},{"style":{"width":"21.613608186047763%","height":"36.722756566888535%","position":"absolute","left":"54.79276927710644%","top":"29.2822012938071%","box-shadow":"none","bottom":"34.19520861692952%","right":"17.0572770190526%"},"contentStyle":{"overflow-y":"visible","padding":"0px 0px 0px 0px","background":"#acd8d1","border-top-left-radius":"85px 26px","border-bottom-left-radius":"40px 40px:::generated:::","border-bottom-right-radius":"40px 40px:::generated:::"},"showHeader":false,"autoZIndex":false,"type":"BACKGROUND"},{"style":{"width":"42.87692708432597%","height":"17.944998854551137%","position":"absolute","left":"11.49453999893332%","top":"26.73316602890886%","box-shadow":"none","bottom":"77.05855527537304%","right":"52.446323769223405%"},"contentStyle":{"overflow-y":"visible","padding":"0px 0px 0px 0px","background":"#50d1d","border-top-left-radius":"21px 18px","border-bottom-left-radius":"40px 40px:::generated:::","border-bottom-right-radius":"40px 40px:::generated:::"},"showHeader":false,"autoZIndex":false,"type":"BACKGROUND"},{"style":{"width":"31.16855846010575%","height":"13.520415095171153%","position":"absolute","left":"21.45974200690045%","top":"38.540026038970126%","box-shadow":"none","bottom":"38.5221952799087%","right":"64.00925027686%"},"contentStyle":{"overflow-y":"visible","padding":"0px 0px 0px 0px","background":"#6838cb","border-top-left-radius":"6px 9px","border-bottom-left-radius":"40px 40px:::generated:::","border-bottom-right-radius":"40px 40px:::generated:::"},"showHeader":false,"autoZIndex":false,"type":"BACKGROUND"},{"style":{"width":"47.60020295539882%","height":"56.200347082691216%","position":"absolute","left":"49.173807674648444%","top":"10.243293624325432%","box-shadow":"none","bottom":"37.519861510227486%","right":"45.412719520230105%"},"textStyle":{"text-align":"center","font-size":"0.3350440431765407rem","font-weight":"bold"},"contentStyle":{"overflow-y":"visible","padding":"0px 0px 0px 0px","background":"rgb(0 0 0 / 0%)","color":"#71717e"},"type":"TEXT","text":"fAF","showHeader":false,"autoZIndex":false},{"style":{"width":"8.579977237975612%","height":"3.075419862289216%","position":"absolute","left":"24.701388749892757%","top":"47.662091251620105%","box-shadow":"none","bottom":"84.25644255878242%","right":"58.95648313458796%"},"textStyle":{"text-align":"center","font-size":"2.901696406488386rem","font-weight":"bold"},"contentStyle":{"overflow-y":"visible","padding":"0px 0px 0px 0px","background":"rgb(0 0 0 / 0%)","color":"#8c4d87"},"type":"TEXT","text":"m0Tt","showHeader":false,"autoZIndex":false},{"style":{"width":"23.591569030357775%","height":"11.123900499998548%","position":"absolute","left":"2.5668508765871394%","top":"25.86918394487646%","box-shadow":"none","bottom":"8.495749054538372%","right":"21.787465754772754%"},"textStyle":{"text-align":"center","font-size":"0.8035267334662737rem","font-weight":"bold"},"contentStyle":{"overflow-y":"visible","padding":"0px 0px 0px 0px","background":"rgb(0 0 0 / 0%)","color":"#b68390"},"type":"TEXT","text":"2hovA","showHeader":false,"autoZIndex":false},{"style":{"width":"49.8856026340505%","height":"16.71364501951198%","position":"absolute","left":"15.888850009696384%","top":"38.337488789199895%","box-shadow":"none","bottom":"49.472578702938875%","right":"6.374656448042543%"},"textStyle":{"text-align":"center","font-size":"1.990055788055085rem","font-weight":"bold"},"contentStyle":{"overflow-y":"visible","padding":"0px 0px 0px 0px","background":"rgb(0 0 0 / 0%)","color":"#b307ff"},"type":"TEXT","text":"Y","showHeader":false,"autoZIndex":false},{"style":{"width":"39.028553830790294%","height":"24.01175710548428%","position":"absolute","left":"35.095941636387124%","top":"62.68632479807075%","box-shadow":"none","bottom":"48.32266096222129%","right":"22.41266728900684%"},"textStyle":{"text-align":"center","font-size":"1.6798227071178997rem","font-weight":"bold"},"contentStyle":{"overflow-y":"visible","padding":"0px 0px 0px 0px","background":"rgb(0 0 0 / 0%)","color":"#f75867"},"type":"TEXT","text":"cgcVW","showHeader":false,"autoZIndex":false},{"style":{"width":"3.2847661365007284%","height":"31.77765981472445%","position":"absolute","left":"29.666046630114963%","top":"23.655122297739723%","box-shadow":"none","bottom":"63.17951456257237%","right":"57.81381408319287%"},"textStyle":{"text-align":"center","font-size":"2.4773545389731484rem","font-weight":"bold"},"contentStyle":{"overflow-y":"visible","padding":"0px 0px 0px 0px","background":"rgb(0 0 0 / 0%)","color":"#d23ac3"},"type":"TEXT","text":"pi","showHeader":false,"autoZIndex":false},{"style":{"width":"4.9466939539841945%","height":"4.5274271212154815%","position":"absolute","left":"56.766162719582276%","top":"67.33734914800749%","box-shadow":"none","bottom":"43.195031405822654%","right":"77.56547789235347%"},"textStyle":{"text-align":"center","font-size":"2.9574142328204664rem","font-weight":"bold"},"contentStyle":{"overflow-y":"visible","padding":"0px 0px 0px 0px","background":"rgb(0 0 0 / 0%)","color":"#f2c0b3"},"type":"TEXT","text":"0","showHeader":false,"autoZIndex":false},{"style":{"width":"6.17960536326725%","height":"15.03498304103126%","position":"absolute","left":"7.12224403675129%","top":"17.66614914518621%","box-shadow":"none","bottom":"64.65566641382931%","right":"13.4275059448617%"},"textStyle":{"text-align":"center","font-size":"2.2996765182199845rem","font-weight":"bold"},"contentStyle":{"overflow-y":"visible","padding":"0px 0px 0px 0px","background":"rgb(0 0 0 / 0%)","color":"#1b5119"},"type":"TEXT","text":"B","showHeader":false,"autoZIndex":false},{"style":{"width":"22.945741298956946%","height":"30.57776153649315%","position":"absolute","left":"10.077976148113223%","top":"42.3863494559861%","box-shadow":"none","bottom":"19.12469909382677%","right":"47.68584736986176%"},"textStyle":{"text-align":"center","font-size":"1.0605672338512473rem","font-weight":"bold"},"contentStyle":{"overflow-y":"visible","padding":"0px 0px 0px 0px","background":"rgb(0 0 0 / 0%)","color":"#93cf98"},"type":"TEXT","text":"y3TjrEF","showHeader":false,"autoZIndex":false},{"style":{"width":"5.414701635713854%","height":"37.31621156794899%","position":"absolute","left":"25.761348899037763%","top":"34.19152082190062%","box-shadow":"none","bottom":"21.39552940292343%","right":"44.83368487038132%"},"textStyle":{"text-align":"center","font-size":"2.391950365130134rem","font-weight":"bold"},"contentStyle":{"overflow-y":"visible","padding":"0px 0px 0px 0px","background":"rgb(0 0 0 / 0%)","color":"#f085a3"},"type":"TEXT","text":"aL","showHeader":false,"autoZIndex":false}]